LICENSE
README.md
netbox_tunnels/__init__.py
netbox_tunnels/admin.py
netbox_tunnels/choices.py
netbox_tunnels/filters.py
netbox_tunnels/forms.py
netbox_tunnels/migrations/0001_initial.py
netbox_tunnels/migrations/__init__.py
netbox_tunnels/models.py
netbox_tunnels/navigation.py
netbox_tunnels/tables.py
netbox_tunnels/template_content.py
netbox_tunnels/templates/netbox_tunnels/device_tunnel_list.html
netbox_tunnels/templates/netbox_tunnels/tunnel_edit.html
netbox_tunnels/templates/netbox_tunnels/tunnels_list.html
netbox_tunnels/urls.py
netbox_tunnels/views.py
netbox_tunnels_plugin-0.3.6.dist-info/LICENSE
netbox_tunnels_plugin-0.3.6.dist-info/WHEEL
netbox_tunnels_plugin-0.3.6.dist-info/METADATA
netbox_tunnels_plugin-0.3.6.dist-info/RECORD
