Metadata-Version: 2.1
Name: netbox-tunnels-plugin
Version: 0.3.6
Summary: A plugin for Netbox to document network tunnels
Home-page: https://github.com/jdrew82/netbox-tunnels-plugin
License: Apache-2.0
Keywords: netbox,network,tunnels,django
Author: Justin Drew
Author-email: jdrew82@users.noreply.github.com
Requires-Python: >=3.6,<4.0
Classifier: License :: OSI Approved :: Apache Software License
Classifier: Programming Language :: Python :: 3
Classifier: Programming Language :: Python :: 3.6
Classifier: Programming Language :: Python :: 3.7
Classifier: Programming Language :: Python :: 3.8
Requires-Dist: invoke (>=1.4.1,<2.0.0)
Project-URL: Repository, https://github.com/jdrew82/netbox-tunnels-plugin
